fid/__init__.py
fid/fid.py
fid/welcome.py
fid_ffmpeg-0.4.0.dist-info/licenses/LICENSE
fid_ffmpeg-0.4.0.dist-info/METADATA
fid_ffmpeg-0.4.0.dist-info/WHEEL
fid_ffmpeg-0.4.0.dist-info/entry_points.txt
fid_ffmpeg-0.4.0.dist-info/top_level.txt
fid_ffmpeg-0.4.0.dist-info/RECORD
