Metadata-Version: 2.4
Name: fid-ffmpeg
Version: 0.4.0
Summary:  based ffmpeg CLI for video operations
Author-email: omar_abdalgwad <ahlawyomar95@gmail.com>
License-File: LICENSE
Requires-Dist: typer>=0.7
Dynamic: license-file
